fcengine.py
fcengine-1.0.dist-info/WHEEL
fcengine-1.0.dist-info/METADATA
fcengine-1.0.dist-info/RECORD
